exceptiongen/__init__.py
exceptiongenerator-2.3.dist-info/DESCRIPTION.rst
exceptiongenerator-2.3.dist-info/METADATA
exceptiongenerator-2.3.dist-info/RECORD
exceptiongenerator-2.3.dist-info/WHEEL
exceptiongenerator-2.3.dist-info/metadata.json
exceptiongenerator-2.3.dist-info/top_level.txt
exceptiongenerator-2.3.dist-info/zip-safe
