Metadata-Version: 2.0
Name: exceptiongenerator
Version: 2.3
Summary: Easy way to generate exceptions that just have a message
Home-page: https://github.com/Poketec/ExceptionGenerator
Author: PokestarFan
Author-email: pokestarfan@yahoo.com
License: MIT
Platform: UNKNOWN
